{
    "settings": {
        "baseUrl": "http://localhost:3000",
        "defaultRoute": "/recent",
        "menuSource": "",
        "skin": "",
        "logo": "/img/logo.png",
        "logo_w": "/img/logo-w.png",
        "enableDarkOption": false,
        "closeOnScroll": false,
        "nondefault": false
    },
    "menu": [{
            "Description": "Höre aktuelle und zuletzt erschienene Folgen",
            "Name": "Hör rein",
            "Replaces": "Hör rein",
            "link": "/recent",
            "menu_items": [
                {
                    "Name": "Aktuelle Folgen",
                    "locale": "de",
                    "link": "/recent",
                    "local": true
                },
                {
                    "Name": "Aktuelle Serien",
                    "locale": "de",
                    "link": "/series",
                    "local": true
                },
                {
                    "Name": "Podcasts",
                    "locale": "de",
                    "link": "/podcasts",
                    "local": true
                }
            ]
        },
        {
            "Description": "Podcasts, Serien und Folgen verwalten ",
            "Name": "Administrator",
            "admin": true,
            "link": "/admin",
            "menu_items": [
                {
                    "Name": "Andministrator Login",
                    "locale": "de",
                    "loggedin": false,
                    "link": "/admin/login",
                    "local": true
                },
                {
                    "Name": "Passwort ändern",
                    "loggedin": true,
                    "locale": "de",
                    "link": "/admin/setpassword",
                    "local": true
                },
                {
                    "Name": "Benutzer einladen",
                    "locale": "de",
                    "loggedin": true,
                    "link": "/admin/invitation",
                    "local": true
                },
                {
                    "Name": "Abmelden",
                    "locale": "de",
                    "loggedin": true,
                    "link": "#logout",
                    "local": true
                }
            ]
        }
    ]
}